{
    "status": "ok",
    "totalResults": 70,
    "articles": [
        {
            "source": {
                "id": null,
                "name": "NBCSports.com"
            },
            "author": "Charean Williams",
            "title": "Report: Ja'Marr Chase will miss time with a separated shoulder - NBC Sports",
            "description": "The Bengals star receiver has 93 catches for 1,156 yards and seven touchdowns this season.",
            "url": "https://www.nbcsports.com/nfl/profootballtalk/rumor-mill/news/report-jamarr-chase-will-miss-time-with-a-separated-shoulder",
            "urlToImage": "https://nbcsports.brightspotcdn.com/dims4/default/925ae66/2147483647/strip/true/crop/6149x3459+0+0/resize/1440x810!/quality/90/?url=https%3A%2F%2Fnbc-sports-production-nbc-sports.s3.us-east-1.amazonaws.com%2Fbrightspot%2F2e%2F4c%2Fc8668fd5498cbfd03cbbaf37d5dc%2Fhttps-api-imagn.com%2Frest%2Fdownload%2FimageID%3D22119567",
            "publishedAt": "2023-12-19T03:41:23Z",
            "content": "The hits keep coming for the Bengals, who have managed to stay in playoff contention without quarterback Joe Burrow. \r\nNow, they will have to try to do it without star receiver JaMarr Chase.\r\nIan Rap… [+750 chars]"
        },
        {
            "source": {
                "id": null,
                "name": "YouTube"
            },
            "author": null,
            "title": "Harden (35 PTS), George (27 PTS), & Kawhi (28 PTS) Combine For 90 Points! 🔥 | December 18, 2023 - NBA",
            "description": null,
            "url": "https://www.youtube.com/watch?v=KTslVAUdSP8",
            "urlToImage": null,
            "publishedAt": "2023-12-19T03:27:59Z",
            "content": "Your browser isnt supported anymore. Update it to get the best YouTube experience and our latest features. Learn more\r\nRemind me later"
        },
        {
            "source": {
                "id": null,
                "name": "YouTube"
            },
            "author": null,
            "title": "Montreal Canadiens at Winnipeg Jets | FULL Overtime Highlights - SPORTSNET",
            "description": "Watch the full overtime between the Montreal Canadiens and the Winnipeg Jets from Monday, December 18th, 2023. ----------------------------------------------...",
            "url": "https://www.youtube.com/watch?v=w-qrltcwL1c",
            "urlToImage": "https://i.ytimg.com/vi/w-qrltcwL1c/maxresdefault.jpg",
            "publishedAt": "2023-12-19T03:20:14Z",
            "content": null
        },
        {
            "source": {
                "id": null,
                "name": "YouTube"
            },
            "author": null,
            "title": "Cade Cunningham Drops CAREER-HIGH 43 Points! 🔥 | December 18, 2023 - NBA",
            "description": null,
            "url": "https://www.youtube.com/watch?v=Zqd6ll0WRTQ",
            "urlToImage": null,
            "publishedAt": "2023-12-19T03:19:31Z",
            "content": "Your browser isnt supported anymore. Update it to get the best YouTube experience and our latest features. Learn more\r\nRemind me later"
        },
        {
            "source": {
                "id": null,
                "name": "Flowrestling.org"
            },
            "author": "JD Rader",
            "title": "2023 Wrestling Collegiate Duals Results - FloWrestling",
            "description": "Take a look at all of the results coming out of the Collegiate Duals in Nashville, Tennesse.",
            "url": "https://www.flowrestling.org/articles/11727882-2023-wrestling-collegiate-duals-results",
            "urlToImage": "https://d2779tscntxxsw.cloudfront.net/6580cf9c3793b.png",
            "publishedAt": "2023-12-19T03:11:15Z",
            "content": "The Collegiate Duals are underway in Nashville, Tennessee. One of the best collegiate dual events of the year, it features some of the nation's top D1 teams competing in a round-robin pool play forma… [+4562 chars]"
        },
        {
            "source": {
                "id": null,
                "name": "YouTube"
            },
            "author": null,
            "title": "TIMBERWOLVES at HEAT | FULL GAME HIGHLIGHTS | December 18, 2023 - NBA",
            "description": null,
            "url": "https://www.youtube.com/watch?v=WxQeN4JryAo",
            "urlToImage": null,
            "publishedAt": "2023-12-19T03:03:23Z",
            "content": "Your browser isnt supported anymore. Update it to get the best YouTube experience and our latest features. Learn more\r\nRemind me later"
        },
        {
            "source": {
                "id": null,
                "name": "YouTube"
            },
            "author": null,
            "title": "NHL Highlights | Ducks vs. Red Wings - December 18, 2023 - SPORTSNET",
            "description": null,
            "url": "https://www.youtube.com/watch?v=zJi0hTJD1Hg",
            "urlToImage": null,
            "publishedAt": "2023-12-19T02:52:19Z",
            "content": "Your browser isnt supported anymore. Update it to get the best YouTube experience and our latest features. Learn more\r\nRemind me later"
        },
        {
            "source": {
                "id": null,
                "name": "Yahoo Entertainment"
            },
            "author": null,
            "title": "Fantasy Football Waiver Wire Pickups, Week 16: Priority adds to help you survive and advance in the playoffs - Yahoo Sports",
            "description": null,
            "url": "https://sports.yahoo.com/fantasy-football-waiver-wire-pickups-week-16-priority-adds-to-help-you-survive-and-advance-in-the-playoffs-213254989.html",
            "urlToImage": null,
            "publishedAt": "2023-12-19T02:44:00Z",
            "content": "Si vous cliquez sur « Tout accepter », nos partenaires (y compris 242 qui font partie du Cadre de transparence et de consentement dIAB) et nous utiliserons également des témoins et vos données person… [+982 chars]"
        },
        {
            "source": {
                "id": null,
                "name": "pgatour.com"
            },
            "author": "Paul Hodowanic",
            "title": "Meet the five players who earned their cards at PGA TOUR Q-School presented by Korn Ferry - PGA TOUR",
            "description": "PONTE VEDRA BEACH, Fla. – It’s a feeling that only a few current PGA TOUR pros have felt: earning their TOUR cards at PGA TOUR Q-School presented by Korn Ferry.",
            "url": "https://www.pgatour.com/article/news/latest/2023/12/18/meet-the-five-players-who-earned-their-pga-tour-card-at-pga-tour-q-school-presented-by-korn-ferry",
            "urlToImage": "https://res.cloudinary.com/pgatour-prod/w_1200,h_628,c_fill,f_auto/pgatour/news/editorial/2023/12/18/meetfive-1694NEW.jpg",
            "publishedAt": "2023-12-19T02:23:55Z",
            "content": "PONTE VEDRA BEACH, Fla. Its a feeling that only a few current PGA TOUR pros have felt: earning their TOUR cards at PGA TOUR Q-School presented by Korn Ferry.\r\nFor the last 10 years, Q-School only ser… [+8499 chars]"
        },
        {
            "source": {
                "id": null,
                "name": "Detroit Free Press"
            },
            "author": "Detroit Free Press",
            "title": "Michigan State basketball's stifling defense takes down Oakland, 79-62, at Breslin Center - Detroit Free Press",
            "description": null,
            "url": "https://www.freep.com/story/sports/college/michigan-state/spartans/2023/12/18/michigan-state-basketball-game-recap-oakland-tyson-walker-1000-points/71967084007/",
            "urlToImage": null,
            "publishedAt": "2023-12-19T02:04:50Z",
            "content": null
        },
        {
            "source": {
                "id": null,
                "name": "The Athletic"
            },
            "author": "Bruce Feldman and Max Olson",
            "title": "Dante Moore, former 5-star QB recruit, transferring to Oregon: How he’ll fit with Dillon Gabriel - The Athletic",
            "description": "Moore appeared in nine games and started five for the Bruins as a true freshman.",
            "url": "https://theathletic.com/5147630/2023/12/18/dante-moore-oregon-ucla-transfer/",
            "urlToImage": "https://cdn.theathletic.com/app/uploads/2023/12/18200050/USATSI_21975425-scaled.jpg",
            "publishedAt": "2023-12-19T01:57:12Z",
            "content": "Former UCLA quarterback Dante Moore, a five-star prospect in the Class of 2023, is transferring to Oregon, he announced Monday. Moore was the No. 2 QB available in The Athletics transfer portal ranki… [+2512 chars]"
        },
        {
            "source": {
                "id": null,
                "name": "Nbcsportsbayarea.com"
            },
            "author": "Jennifer Lee Chan",
            "title": "49ers injury report: Davis out multiple weeks with high ankle sprain - NBC Sports Bay Area",
            "description": "The 49ers came away from their 45-29 win over the Arizona Cardinals on Sunday even thinner on the defensive line.",
            "url": "http://www.nbcsportsbayarea.com/nfl/san-francisco-49ers/kalia-davis-injury/1682792/",
            "urlToImage": "https://media.nbcsportsbayarea.com/2023/12/kalia-davis-USATSI_22058096.jpg?quality=85&strip=all&resize=1200%2C675",
            "publishedAt": "2023-12-19T01:44:12Z",
            "content": "The 49ers came away from their 45-29 win over the Arizona Cardinals on Sunday even thinner on the defensive line.\r\nKalia Davis suffered a high ankle sprain in the victory at State Farm Stadium after … [+1911 chars]"
        },
        {
            "source": {
                "id": null,
                "name": "MLB Trade Rumors"
            },
            "author": "Anthony Franco",
            "title": "Giants, Tom Murphy Agree To Two-Year Contract - MLB Trade Rumors",
            "description": "The Giants are in agreement with free agent catcher Tom Murphy on a two-year deal with a 2026 club option, &hellip;",
            "url": "https://www.mlbtraderumors.com/2023/12/giants-tom-murphy-nearing-multi-year-contract.html",
            "urlToImage": "https://cdn.mlbtraderumors.com/files/2023/12/USATSI_20982841-1024x683.jpg",
            "publishedAt": "2023-12-19T01:25:26Z",
            "content": "The Giants are in agreement with free agent catcher Tom Murphy on a two-year deal with a 2026 club option, according to multiple reports. The Ballengee Group client is reportedly guaranteed $8.25MM, … [+3346 chars]"
        },
        {
            "source": {
                "id": null,
                "name": "YouTube"
            },
            "author": null,
            "title": "Micah Parsons Responds to Bills Loss, Calls Out Media Coverage of Cowboys | The Edge, Ep. 15 - Bleacher Report",
            "description": null,
            "url": "https://www.youtube.com/watch?v=Vy8sdTC2V68",
            "urlToImage": null,
            "publishedAt": "2023-12-19T01:06:08Z",
            "content": "Your browser isnt supported anymore. Update it to get the best YouTube experience and our latest features. Learn more\r\nRemind me later"
        },
        {
            "source": {
                "id": "espn",
                "name": "ESPN"
            },
            "author": "Kris Rhim",
            "title": "John Spanos - 'No limitations' on Chargers' coaching, GM hires - ESPN",
            "description": "Chargers team president John Spanos said the team would have \"no limitations\" in replacing fired coach Brandon Staley and GM Tom Telesco.",
            "url": "https://www.espn.com/nfl/story/_/id/39142892/john-spanos-no-limitations-chargers-coaching-gm-hires",
            "urlToImage": "https://a4.espncdn.com/combiner/i?img=%2Fphoto%2F2023%2F1219%2Fr1268198_1024x576_16%2D9.jpg",
            "publishedAt": "2023-12-19T01:05:00Z",
            "content": "COSTA MESA, Calif. -- Los Angeles Chargers president John Spanos said the team would have \"no limitations\" on its next head coach and general manager pairing, from experience to salary, attempting to… [+5687 chars]"
        },
        {
            "source": {
                "id": null,
                "name": "Nbcsportsbayarea.com"
            },
            "author": "Jennifer Lee Chan",
            "title": "How PFF graded Purdy, 49ers in Sunday's win vs. Cardinals - NBC Sports Bay Area",
            "description": "Jennifer Lee Chan details how PFF graded Brock Purdy, Deebo Samuel and the rest of the 49ers in their Week 15 win over the Arizona Cardinals on Sunday.",
            "url": "http://www.nbcsportsbayarea.com/nfl/san-francisco-49ers/brock-purdy-pff-grades-win-cardinals/1682757/",
            "urlToImage": "https://media.nbcsportsbayarea.com/2023/12/brock-purdy-49ers-cardinals-win-GETTY.jpg?quality=85&strip=all&resize=1200%2C675",
            "publishedAt": "2023-12-19T00:59:30Z",
            "content": "It was a heros homecoming both on and off the field for Brock Purdy in the 49ers' 45-29 win in the desert on Sunday. \r\nThe Arizona native received an 86.5 overall PFF grade, bringing his six-week ave… [+4450 chars]"
        },
        {
            "source": {
                "id": null,
                "name": "DawgNation"
            },
            "author": "Connor Riley",
            "title": "Carson Beck announces he will return to Georgia football for senior season - DawgNation",
            "description": "",
            "url": "https://www.DawgNation.com/football/carson-beck-georgia-football-2024/YWEKGSLXNRALPAHWX3SK5FWSEQ/",
            "urlToImage": "https://www.dawgnation.com/resizer/8N0BVsr4xF7jBLPdMywM9WCs8rc=/1280x673/smart/cloudfront-us-east-1.images.arcpublishing.com/ajc/SBIT272OUNG6VM6ECEF2YN2OYE.jpg",
            "publishedAt": "2023-12-19T00:33:36Z",
            "content": null
        },
        {
            "source": {
                "id": null,
                "name": "Prideofdetroit.com"
            },
            "author": "Erik Schlitt",
            "title": "‘Monday Night Football’ picks, playoff implications: Eagles at Seahawks - Pride Of Detroit",
            "description": "POD staff picks for the “Monday Night Football” matchups between the Philadelphia Eagles and Seattle Seahawks.",
            "url": "https://www.prideofdetroit.com/2023/12/18/24001064/monday-night-football-week-15-expert-picks-philadelphia-eagles-at-seattle-seahawks",
            "urlToImage": "https://cdn.vox-cdn.com/thumbor/eYdkUvjZZhbwCvmbZuGXvJni7jQ=/0x280:6233x3543/fit-in/1200x630/cdn.vox-cdn.com/uploads/chorus_asset/file/25170838/1229688307.jpg",
            "publishedAt": "2023-12-19T00:30:00Z",
            "content": "The NFL closes out Week 15 with a Monday Night Football matchup between the Philadelphia Eagles and Seattle Seahawks. This game was originally set to feature the Kansas City Chiefs and New England Pa… [+2146 chars]"
        },
        {
            "source": {
                "id": null,
                "name": "YouTube"
            },
            "author": null,
            "title": "Is the UCL round of 16 draw BORING? 😮 Ale Moreno thinks the Quarterfinals could be 'GREAT' | ESPN FC - ESPN UK",
            "description": "Steve Nicol, Julien Laurens, Mario Melchiot and Ale Moreno join Dan Thomas on ESPN FC to react to the UEFA Champions League round of 16 draw including Copenh...",
            "url": "https://www.youtube.com/watch?v=EH4w_mUhktE",
            "urlToImage": "https://i.ytimg.com/vi/EH4w_mUhktE/maxresdefault.jpg",
            "publishedAt": "2023-12-19T00:01:04Z",
            "content": null
        },
        {
            "source": {
                "id": null,
                "name": "YouTube"
            },
            "author": null,
            "title": "Inside Anfield: Unseen Footage From Draw | Liverpool 0-0 Manchester United - Liverpool FC",
            "description": "Get the best behind-the-scenes footage from the Premier League tie between the Reds and Man Utd, as a record Anfield attendance, including professional golfe...",
            "url": "https://www.youtube.com/watch?v=7COYMxCbuCE",
            "urlToImage": "https://i.ytimg.com/vi/7COYMxCbuCE/maxresdefault.jpg",
            "publishedAt": "2023-12-19T00:00:11Z",
            "content": null
        }
    ]
} 